README.md
setup.py
dilami_calendar/__init__.py
dilami_calendar/algorithms.py
dilami_calendar/constants.py
dilami_calendar/dilami_datetime.py
dilami_calendar/exceptions.py
dilami_calendar/validators.py
dilami_calendar.egg-info/PKG-INFO
dilami_calendar.egg-info/SOURCES.txt
dilami_calendar.egg-info/dependency_links.txt
dilami_calendar.egg-info/requires.txt
dilami_calendar.egg-info/top_level.txt
dilami_calendar/tests/__init__.py
dilami_calendar/tests/test_algorithms.py
dilami_calendar/tests/test_dilami_date.py
dilami_calendar/tests/test_validators.py