Metadata-Version: 2.1
Name: dilami-calendar
Version: 0.4.3
Summary: Dilami (Gilaki) calendar for python
Home-page: http://github.com/jangal/python-dilami-calendar
Author: Jangal
License: UNKNOWN
Keywords: dilami deylami daylami gilaki calendar datetime date time conversion
Platform: UNKNOWN
Classifier: Programming Language :: Python
Classifier: Development Status :: 3 - Alpha
Classifier: License :: OSI Approved :: MIT License
Classifier: Operating System :: OS Independent
Classifier: Programming Language :: Python
Classifier: Programming Language :: Python :: 3.5
Classifier: Programming Language :: Python :: 3.6
Classifier: Programming Language :: Python :: 3.7
Classifier: Programming Language :: Python :: 3.8
Classifier: Programming Language :: Python :: 3.9
Classifier: Intended Audience :: Developers
Classifier: Topic :: Software Development :: Libraries :: Python Modules
Classifier: Topic :: Software Development :: Localization
